{"nodes": [{"id": "functions_admin_dashboard_index", "label": "Admin Dashboard Edge Function", "file_type": "code", "source_file": "supabase/functions/admin-dashboard/index.ts", "source_location": "line 1", "source_url": null, "captured_at": null, "author": null, "contributor": null}], "edges": [{"source": "functions_admin_dashboard_index", "target": "supabase_schema_wiki_notes", "relation": "references", "confidence": "EXTRACTED", "confidence_score": 1.0, "source_file": "supabase/functions/admin-dashboard/index.ts", "source_location": "line 133", "weight": 1.0}, {"source": "functions_admin_dashboard_index", "target": "supabase_schema_plant_knowledge", "relation": "references", "confidence": "EXTRACTED", "confidence_score": 1.0, "source_file": "supabase/functions/admin-dashboard/index.ts", "source_location": "line 133", "weight": 1.0}, {"source": "functions_admin_dashboard_index", "target": "functions_extract_plant_care_index", "relation": "calls", "confidence": "EXTRACTED", "confidence_score": 1.0, "source_file": "supabase/functions/admin-dashboard/index.ts", "source_location": "line 108", "weight": 1.0}], "hyperedges": []}